django_restframework_extended/__init__.py
django_restframework_extended/logging/__init__.py
django_restframework_extended/logging/core.py
django_restframework_extended/models/__init__.py
django_restframework_extended/models/extra.py
django_restframework_extended/views/__init__.py
django_restframework_extended/views/cerberus.py
views/__init__.py
views/cerberus.py
django_restframework_extended-0.0.8.dist-info/METADATA
django_restframework_extended-0.0.8.dist-info/WHEEL
django_restframework_extended-0.0.8.dist-info/top_level.txt
django_restframework_extended-0.0.8.dist-info/RECORD
