Metadata-Version: 2.4
Name: django_restframework_extended
Version: 0.0.8
Summary: Django Rest Framework Extended Functionalities
Author: Manan Lad
Author-email: luckycasualguy@gmail.com
Keywords: python,django,restframework,extended,cerberus
Classifier: Development Status :: 4 - Beta
Classifier: Intended Audience :: Education
Classifier: Programming Language :: Python :: 2
Classifier: Programming Language :: Python :: 3
Classifier: Operating System :: MacOS :: MacOS X
Classifier: Operating System :: Microsoft :: Windows
Dynamic: author
Dynamic: author-email
Dynamic: classifier
Dynamic: description
Dynamic: keywords
Dynamic: summary
